<annotation>
	<folder>fire</folder>
	<filename>images635.jpg</filename>
	<path>C:\Users\ramia\Downloads\fire\fire\images635.jpg</path>
	<source>
		<database>Unknown</database>
	</source>
	<size>
		<width>276</width>
		<height>183</height>
		<depth>3</depth>
	</size>
	<segmented>0</segmented>
	<object>
		<name>smoke</name>
		<pose>Unspecified</pose>
		<truncated>1</truncated>
		<difficult>0</difficult>
		<bndbox>
			<xmin>1</xmin>
			<ymin>40</ymin>
			<xmax>79</xmax>
			<ymax>176</ymax>
		</bndbox>
	</object>
	<object>
		<name>smoke</name>
		<pose>Unspecified</pose>
		<truncated>1</truncated>
		<difficult>0</difficult>
		<bndbox>
			<xmin>86</xmin>
			<ymin>136</ymin>
			<xmax>120</xmax>
			<ymax>183</ymax>
		</bndbox>
	</object>
</annotation>
